[
{
  "model": "machines.machine",
  "pk": 149,
  "fields": {
    "created_at": "2025-08-20T22:47:53.716Z",
    "updated_at": "2025-08-20T22:47:53.716Z",
    "created_by": null,
    "updated_by": null,
    "site_code": "FAB-001",
    "status": "active",
    "machine_id": "AX-AIR-001",
    "name": "Air Compressor 01",
    "machine_type": 49,
    "manufacturer": "Atlas Copco",
    "model_number": "GA75",
    "serial_number": "ATL20242787",
    "installation_date": "2024-03-02",
    "building": "Utility Building",
    "floor": "Floor 1",
    "location_details": "Production Zone A, Line 1",
    "operational_status": "running",
    "total_operating_hours": 12047.9,
    "hours_since_maintenance": 502.0,
    "rated_power": 73.16561331161324,
    "rated_capacity": 1238.1442782278796,
    "capacity_unit": "CFM",
    "last_maintenance_date": null,
    "next_maintenance_date": null,
    "primary_operator": null,
    "notes": "",
    "warranty_expiry": null,
    "purchase_cost": null
  }
},
{
  "model": "machines.machine",
  "pk": 150,
  "fields": {
    "created_at": "2025-08-20T22:47:53.726Z",
    "updated_at": "2025-08-20T22:47:53.726Z",
    "created_by": null,
    "updated_by": null,
    "site_code": "FAB-001",
    "status": "active",
    "machine_id": "AX-HUM-002",
    "name": "Humidification System 02",
    "machine_type": 50,
    "manufacturer": "Munters",
    "model_number": "ML270",
    "serial_number": "MUN20241027",
    "installation_date": "2024-01-04",
    "building": "Utility Building",
    "floor": "Floor 2",
    "location_details": "Production Zone B, Line 2",
    "operational_status": "idle",
    "total_operating_hours": 12660.5,
    "hours_since_maintenance": 291.0,
    "rated_power": 27.935675572809952,
    "rated_capacity": 1920.340400309291,
    "capacity_unit": "kg/hr",
    "last_maintenance_date": null,
    "next_maintenance_date": null,
    "primary_operator": null,
    "notes": "",
    "warranty_expiry": null,
    "purchase_cost": null
  }
},
{
  "model": "machines.machine",
  "pk": 127,
  "fields": {
    "created_at": "2025-08-20T22:47:53.500Z",
    "updated_at": "2025-08-20T22:47:53.500Z",
    "created_by": null,
    "updated_by": null,
    "site_code": "FAB-001",
    "status": "active",
    "machine_id": "CP-CAR-002",
    "name": "Carding Machine 02",
    "machine_type": 42,
    "manufacturer": "Rieter",
    "model_number": "C80",
    "serial_number": "RIE20198285",
    "installation_date": "2019-03-07",
    "building": "Raw Material Processing Building",
    "floor": "Floor 2",
    "location_details": "Production Zone B, Line 2",
    "operational_status": "idle",
    "total_operating_hours": 42796.5,
    "hours_since_maintenance": 239.0,
    "rated_power": 100.9304960800431,
    "rated_capacity": 193.29585399162616,
    "capacity_unit": "kg/hr",
    "last_maintenance_date": null,
    "next_maintenance_date": null,
    "primary_operator": null,
    "notes": "",
    "warranty_expiry": null,
    "purchase_cost": null
  }
},
{
  "model": "machines.machine",
  "pk": 129,
  "fields": {
    "created_at": "2025-08-20T22:47:53.517Z",
    "updated_at": "2025-08-20T22:47:53.517Z",
    "created_by": null,
    "updated_by": null,
    "site_code": "FAB-001",
    "status": "active",
    "machine_id": "CP-CAR-004",
    "name": "Carding Machine 04",
    "machine_type": 42,
    "manufacturer": "Rieter",
    "model_number": "TC15",
    "serial_number": "RIE20193608",
    "installation_date": "2019-05-13",
    "building": "Raw Material Processing Building",
    "floor": "Floor 1",
    "location_details": "Production Zone D, Line 4",
    "operational_status": "idle",
    "total_operating_hours": 40395.5,
    "hours_since_maintenance": 77.0,
    "rated_power": 100.27327653121611,
    "rated_capacity": 206.36697407952917,
    "capacity_unit": "kg/hr",
    "last_maintenance_date": null,
    "next_maintenance_date": null,
    "primary_operator": null,
    "notes": "",
    "warranty_expiry": null,
    "purchase_cost": null
  }
},
{
  "model": "machines.machine",
  "pk": 126,
  "fields": {
    "created_at": "2025-08-20T22:47:53.491Z",
    "updated_at": "2025-08-20T22:47:53.491Z",
    "created_by": null,
    "updated_by": null,
    "site_code": "FAB-001",
    "status": "active",
    "machine_id": "CP-DRA-001",
    "name": "Draw Frame 01",
    "machine_type": 43,
    "manufacturer": "Rieter",
    "model_number": "D45",
    "serial_number": "RIE20197331",
    "installation_date": "2019-11-03",
    "building": "Raw Material Processing Building",
    "floor": "Floor 1",
    "location_details": "Production Zone A, Line 1",
    "operational_status": "running",
    "total_operating_hours": 37667.4,
    "hours_since_maintenance": 505.0,
    "rated_power": 44.14704749029341,
    "rated_capacity": 147.13770333995197,
    "capacity_unit": "kg/hr",
    "last_maintenance_date": null,
    "next_maintenance_date": null,
    "primary_operator": null,
    "notes": "",
    "warranty_expiry": null,
    "purchase_cost": null
  }
},
{
  "model": "machines.machine",
  "pk": 128,
  "fields": {
    "created_at": "2025-08-20T22:47:53.508Z",
    "updated_at": "2025-08-20T22:47:53.508Z",
    "created_by": null,
    "updated_by": null,
    "site_code": "FAB-001",
    "status": "active",
    "machine_id": "CP-DRA-003",
    "name": "Draw Frame 03",
    "machine_type": 43,
    "manufacturer": "Rieter",
    "model_number": "D45",
    "serial_number": "RIE20199926",
    "installation_date": "2019-02-11",
    "building": "Raw Material Processing Building",
    "floor": "Floor 3",
    "location_details": "Production Zone C, Line 3",
    "operational_status": "running",
    "total_operating_hours": 42039.0,
    "hours_since_maintenance": 287.0,
    "rated_power": 44.64520766152835,
    "rated_capacity": 156.50577975899594,
    "capacity_unit": "kg/hr",
    "last_maintenance_date": null,
    "next_maintenance_date": null,
    "primary_operator": null,
    "notes": "",
    "warranty_expiry": null,
    "purchase_cost": null
  }
},
{
  "model": "machines.machine",
  "pk": 148,
  "fields": {
    "created_at": "2025-08-20T22:47:53.706Z",
    "updated_at": "2025-08-20T22:47:53.706Z",
    "created_by": null,
    "updated_by": null,
    "site_code": "FAB-001",
    "status": "active",
    "machine_id": "DY-JET-001",
    "name": "Jet Dyeing Machine 01",
    "machine_type": 48,
    "manufacturer": "Thies",
    "model_number": "then",
    "serial_number": "THI20247577",
    "installation_date": "2024-03-29",
    "building": "Wet Processing Building C",
    "floor": "Floor 1",
    "location_details": "Production Zone A, Line 1",
    "operational_status": "running",
    "total_operating_hours": 7077.3,
    "hours_since_maintenance": 9.0,
    "rated_power": 206.25532489037326,
    "rated_capacity": 486.48421577320516,
    "capacity_unit": "kg/hr",
    "last_maintenance_date": null,
    "next_maintenance_date": null,
    "primary_operator": null,
    "notes": "",
    "warranty_expiry": null,
    "purchase_cost": null
  }
},
{
  "model": "machines.machine",
  "pk": 132,
  "fields": {
    "created_at": "2025-08-20T22:47:53.545Z",
    "updated_at": "2025-08-20T22:47:53.545Z",
    "created_by": null,
    "updated_by": null,
    "site_code": "FAB-001",
    "status": "active",
    "machine_id": "SP-RIN-003",
    "name": "Ring Spinning Frame 03",
    "machine_type": 44,
    "manufacturer": "Rieter",
    "model_number": "K45",
    "serial_number": "RIE20196620",
    "installation_date": "2019-01-20",
    "building": "Spinning Mill Building A",
    "floor": "Floor 3",
    "location_details": "Production Zone C, Line 3",
    "operational_status": "idle",
    "total_operating_hours": 48381.4,
    "hours_since_maintenance": 449.0,
    "rated_power": 138.65705017829043,
    "rated_capacity": 24.06403568881556,
    "capacity_unit": "kg/hr",
    "last_maintenance_date": null,
    "next_maintenance_date": null,
    "primary_operator": null,
    "notes": "",
    "warranty_expiry": null,
    "purchase_cost": null
  }
},
{
  "model": "machines.machine",
  "pk": 133,
  "fields": {
    "created_at": "2025-08-20T22:47:53.555Z",
    "updated_at": "2025-08-20T22:47:53.555Z",
    "created_by": null,
    "updated_by": null,
    "site_code": "FAB-001",
    "status": "active",
    "machine_id": "SP-RIN-004",
    "name": "Ring Spinning Frame 04",
    "machine_type": 44,
    "manufacturer": "Rieter",
    "model_number": "G38",
    "serial_number": "RIE20193033",
    "installation_date": "2019-01-14",
    "building": "Spinning Mill Building A",
    "floor": "Floor 1",
    "location_details": "Production Zone D, Line 4",
    "operational_status": "idle",
    "total_operating_hours": 45247.2,
    "hours_since_maintenance": 1.0,
    "rated_power": 135.19060033729286,
    "rated_capacity": 25.747725035364216,
    "capacity_unit": "kg/hr",
    "last_maintenance_date": null,
    "next_maintenance_date": null,
    "primary_operator": null,
    "notes": "",
    "warranty_expiry": null,
    "purchase_cost": null
  }
},
{
  "model": "machines.machine",
  "pk": 139,
  "fields": {
    "created_at": "2025-08-20T22:47:53.615Z",
    "updated_at": "2025-08-20T22:47:53.615Z",
    "created_by": null,
    "updated_by": null,
    "site_code": "FAB-001",
    "status": "active",
    "machine_id": "SP-RIN-010",
    "name": "Ring Spinning Frame 10",
    "machine_type": 44,
    "manufacturer": "Rieter",
    "model_number": "G38",
    "serial_number": "RIE20216553",
    "installation_date": "2021-08-18",
    "building": "Spinning Mill Building A",
    "floor": "Floor 1",
    "location_details": "Production Zone B, Line 5",
    "operational_status": "running",
    "total_operating_hours": 30407.5,
    "hours_since_maintenance": 190.0,
    "rated_power": 160.81288405694585,
    "rated_capacity": 24.735887781246515,
    "capacity_unit": "kg/hr",
    "last_maintenance_date": null,
    "next_maintenance_date": null,
    "primary_operator": null,
    "notes": "",
    "warranty_expiry": null,
    "purchase_cost": null
  }
},
{
  "model": "machines.machine",
  "pk": 140,
  "fields": {
    "created_at": "2025-08-20T22:47:53.626Z",
    "updated_at": "2025-08-20T22:47:53.626Z",
    "created_by": null,
    "updated_by": null,
    "site_code": "FAB-001",
    "status": "active",
    "machine_id": "SP-RIN-011",
    "name": "Ring Spinning Frame 11",
    "machine_type": 44,
    "manufacturer": "Rieter",
    "model_number": "K45",
    "serial_number": "RIE20212508",
    "installation_date": "2021-10-01",
    "building": "Spinning Mill Building A",
    "floor": "Floor 2",
    "location_details": "Production Zone C, Line 1",
    "operational_status": "running",
    "total_operating_hours": 27640.4,
    "hours_since_maintenance": 569.0,
    "rated_power": 148.86973866167017,
    "rated_capacity": 24.81295753693887,
    "capacity_unit": "kg/hr",
    "last_maintenance_date": null,
    "next_maintenance_date": null,
    "primary_operator": null,
    "notes": "",
    "warranty_expiry": null,
    "purchase_cost": null
  }
},
{
  "model": "machines.machine",
  "pk": 141,
  "fields": {
    "created_at": "2025-08-20T22:47:53.638Z",
    "updated_at": "2025-08-20T22:47:53.638Z",
    "created_by": null,
    "updated_by": null,
    "site_code": "FAB-001",
    "status": "active",
    "machine_id": "SP-RIN-012",
    "name": "Ring Spinning Frame 12",
    "machine_type": 44,
    "manufacturer": "Rieter",
    "model_number": "G35",
    "serial_number": "RIE20215853",
    "installation_date": "2021-02-07",
    "building": "Spinning Mill Building A",
    "floor": "Floor 3",
    "location_details": "Production Zone D, Line 2",
    "operational_status": "running",
    "total_operating_hours": 31730.8,
    "hours_since_maintenance": 711.0,
    "rated_power": 135.7225813139093,
    "rated_capacity": 24.943933592527202,
    "capacity_unit": "kg/hr",
    "last_maintenance_date": null,
    "next_maintenance_date": null,
    "primary_operator": null,
    "notes": "",
    "warranty_expiry": null,
    "purchase_cost": null
  }
},
{
  "model": "machines.machine",
  "pk": 130,
  "fields": {
    "created_at": "2025-08-20T22:47:53.526Z",
    "updated_at": "2025-08-20T22:47:53.526Z",
    "created_by": null,
    "updated_by": null,
    "site_code": "FAB-001",
    "status": "active",
    "machine_id": "SP-ROT-001",
    "name": "Rotor Spinning Machine 01",
    "machine_type": 45,
    "manufacturer": "Rieter",
    "model_number": "BD-200",
    "serial_number": "RIE20199441",
    "installation_date": "2019-10-12",
    "building": "Spinning Mill Building A",
    "floor": "Floor 1",
    "location_details": "Production Zone A, Line 1",
    "operational_status": "idle",
    "total_operating_hours": 42297.5,
    "hours_since_maintenance": 56.0,
    "rated_power": 124.97400481811036,
    "rated_capacity": 40.020392005649114,
    "capacity_unit": "kg/hr",
    "last_maintenance_date": null,
    "next_maintenance_date": null,
    "primary_operator": null,
    "notes": "",
    "warranty_expiry": null,
    "purchase_cost": null
  }
},
{
  "model": "machines.machine",
  "pk": 131,
  "fields": {
    "created_at": "2025-08-20T22:47:53.534Z",
    "updated_at": "2025-08-20T22:47:55.770Z",
    "created_by": null,
    "updated_by": null,
    "site_code": "FAB-001",
    "status": "active",
    "machine_id": "SP-ROT-002",
    "name": "Rotor Spinning Machine 02",
    "machine_type": 45,
    "manufacturer": "Rieter",
    "model_number": "R35",
    "serial_number": "RIE20195186",
    "installation_date": "2019-06-15",
    "building": "Spinning Mill Building A",
    "floor": "Floor 2",
    "location_details": "Production Zone B, Line 2",
    "operational_status": "idle",
    "total_operating_hours": 46693.7,
    "hours_since_maintenance": 0.0,
    "rated_power": 113.46581724013801,
    "rated_capacity": 39.124841482097274,
    "capacity_unit": "kg/hr",
    "last_maintenance_date": "2025-08-20T22:47:55.778Z",
    "next_maintenance_date": null,
    "primary_operator": null,
    "notes": "",
    "warranty_expiry": null,
    "purchase_cost": null
  }
},
{
  "model": "machines.machine",
  "pk": 134,
  "fields": {
    "created_at": "2025-08-20T22:47:53.564Z",
    "updated_at": "2025-08-20T22:47:53.564Z",
    "created_by": null,
    "updated_by": null,
    "site_code": "FAB-001",
    "status": "active",
    "machine_id": "SP-ROT-005",
    "name": "Rotor Spinning Machine 05",
    "machine_type": 45,
    "manufacturer": "Rieter",
    "model_number": "R35",
    "serial_number": "RIE20193593",
    "installation_date": "2019-05-17",
    "building": "Spinning Mill Building A",
    "floor": "Floor 2",
    "location_details": "Production Zone A, Line 5",
    "operational_status": "running",
    "total_operating_hours": 45896.9,
    "hours_since_maintenance": 8.0,
    "rated_power": 125.23261087456513,
    "rated_capacity": 38.91608903939832,
    "capacity_unit": "kg/hr",
    "last_maintenance_date": null,
    "next_maintenance_date": null,
    "primary_operator": null,
    "notes": "",
    "warranty_expiry": null,
    "purchase_cost": null
  }
},
{
  "model": "machines.machine",
  "pk": 135,
  "fields": {
    "created_at": "2025-08-20T22:47:53.574Z",
    "updated_at": "2025-08-20T22:47:53.574Z",
    "created_by": null,
    "updated_by": null,
    "site_code": "FAB-001",
    "status": "active",
    "machine_id": "SP-ROT-006",
    "name": "Rotor Spinning Machine 06",
    "machine_type": 45,
    "manufacturer": "Rieter",
    "model_number": "R35",
    "serial_number": "RIE20197215",
    "installation_date": "2019-05-12",
    "building": "Spinning Mill Building A",
    "floor": "Floor 3",
    "location_details": "Production Zone B, Line 1",
    "operational_status": "running",
    "total_operating_hours": 44047.3,
    "hours_since_maintenance": 436.0,
    "rated_power": 111.65114203088899,
    "rated_capacity": 41.555981683864054,
    "capacity_unit": "kg/hr",
    "last_maintenance_date": null,
    "next_maintenance_date": null,
    "primary_operator": null,
    "notes": "",
    "warranty_expiry": null,
    "purchase_cost": null
  }
},
{
  "model": "machines.machine",
  "pk": 136,
  "fields": {
    "created_at": "2025-08-20T22:47:53.584Z",
    "updated_at": "2025-08-20T22:47:53.584Z",
    "created_by": null,
    "updated_by": null,
    "site_code": "FAB-001",
    "status": "active",
    "machine_id": "SP-ROT-007",
    "name": "Rotor Spinning Machine 07",
    "machine_type": 45,
    "manufacturer": "Rieter",
    "model_number": "R40",
    "serial_number": "RIE20216713",
    "installation_date": "2021-03-04",
    "building": "Spinning Mill Building A",
    "floor": "Floor 1",
    "location_details": "Production Zone C, Line 2",
    "operational_status": "idle",
    "total_operating_hours": 31137.3,
    "hours_since_maintenance": 402.0,
    "rated_power": 115.93234455781975,
    "rated_capacity": 40.75540036721065,
    "capacity_unit": "kg/hr",
    "last_maintenance_date": null,
    "next_maintenance_date": null,
    "primary_operator": null,
    "notes": "",
    "warranty_expiry": null,
    "purchase_cost": null
  }
},
{
  "model": "machines.machine",
  "pk": 137,
  "fields": {
    "created_at": "2025-08-20T22:47:53.594Z",
    "updated_at": "2025-08-20T22:47:53.594Z",
    "created_by": null,
    "updated_by": null,
    "site_code": "FAB-001",
    "status": "active",
    "machine_id": "SP-ROT-008",
    "name": "Rotor Spinning Machine 08",
    "machine_type": 45,
    "manufacturer": "Rieter",
    "model_number": "R40",
    "serial_number": "RIE20213772",
    "installation_date": "2021-01-25",
    "building": "Spinning Mill Building A",
    "floor": "Floor 2",
    "location_details": "Production Zone D, Line 3",
    "operational_status": "running",
    "total_operating_hours": 32678.7,
    "hours_since_maintenance": 115.0,
    "rated_power": 110.39293714500648,
    "rated_capacity": 38.72052909990793,
    "capacity_unit": "kg/hr",
    "last_maintenance_date": null,
    "next_maintenance_date": null,
    "primary_operator": null,
    "notes": "",
    "warranty_expiry": null,
    "purchase_cost": null
  }
},
{
  "model": "machines.machine",
  "pk": 138,
  "fields": {
    "created_at": "2025-08-20T22:47:53.605Z",
    "updated_at": "2025-08-20T22:47:53.605Z",
    "created_by": null,
    "updated_by": null,
    "site_code": "FAB-001",
    "status": "active",
    "machine_id": "SP-ROT-009",
    "name": "Rotor Spinning Machine 09",
    "machine_type": 45,
    "manufacturer": "Rieter",
    "model_number": "R35",
    "serial_number": "RIE20218524",
    "installation_date": "2021-02-26",
    "building": "Spinning Mill Building A",
    "floor": "Floor 3",
    "location_details": "Production Zone A, Line 4",
    "operational_status": "idle",
    "total_operating_hours": 33610.0,
    "hours_since_maintenance": 454.0,
    "rated_power": 108.88848251405332,
    "rated_capacity": 39.35426642162973,
    "capacity_unit": "kg/hr",
    "last_maintenance_date": null,
    "next_maintenance_date": null,
    "primary_operator": null,
    "notes": "",
    "warranty_expiry": null,
    "purchase_cost": null
  }
},
{
  "model": "machines.machine",
  "pk": 142,
  "fields": {
    "created_at": "2025-08-20T22:47:53.647Z",
    "updated_at": "2025-08-20T22:47:53.647Z",
    "created_by": null,
    "updated_by": null,
    "site_code": "FAB-001",
    "status": "active",
    "machine_id": "WV-AIR-001",
    "name": "Air Jet Loom 01",
    "machine_type": 46,
    "manufacturer": "Picanol",
    "model_number": "JAT810",
    "serial_number": "PIC20234926",
    "installation_date": "2023-02-23",
    "building": "Weaving Shed Building B",
    "floor": "Floor 1",
    "location_details": "Production Zone A, Line 1",
    "operational_status": "idle",
    "total_operating_hours": 14075.8,
    "hours_since_maintenance": 174.0,
    "rated_power": 11.42170134115203,
    "rated_capacity": 4.667445640633091,
    "capacity_unit": "m/min",
    "last_maintenance_date": null,
    "next_maintenance_date": null,
    "primary_operator": null,
    "notes": "",
    "warranty_expiry": null,
    "purchase_cost": null
  }
},
{
  "model": "machines.machine",
  "pk": 143,
  "fields": {
    "created_at": "2025-08-20T22:47:53.655Z",
    "updated_at": "2025-08-20T22:47:53.655Z",
    "created_by": null,
    "updated_by": null,
    "site_code": "FAB-001",
    "status": "active",
    "machine_id": "WV-AIR-002",
    "name": "Air Jet Loom 02",
    "machine_type": 46,
    "manufacturer": "Picanol",
    "model_number": "OptiMax-i",
    "serial_number": "PIC20236110",
    "installation_date": "2023-04-03",
    "building": "Weaving Shed Building B",
    "floor": "Floor 2",
    "location_details": "Production Zone B, Line 2",
    "operational_status": "running",
    "total_operating_hours": 13776.9,
    "hours_since_maintenance": 457.0,
    "rated_power": 13.125970533088058,
    "rated_capacity": 4.642411493338663,
    "capacity_unit": "m/min",
    "last_maintenance_date": null,
    "next_maintenance_date": null,
    "primary_operator": null,
    "notes": "",
    "warranty_expiry": null,
    "purchase_cost": null
  }
},
{
  "model": "machines.machine",
  "pk": 144,
  "fields": {
    "created_at": "2025-08-20T22:47:53.667Z",
    "updated_at": "2025-08-20T22:47:53.667Z",
    "created_by": null,
    "updated_by": null,
    "site_code": "FAB-001",
    "status": "active",
    "machine_id": "WV-AIR-003",
    "name": "Air Jet Loom 03",
    "machine_type": 46,
    "manufacturer": "Picanol",
    "model_number": "JAT810",
    "serial_number": "PIC20233120",
    "installation_date": "2023-02-27",
    "building": "Weaving Shed Building B",
    "floor": "Floor 3",
    "location_details": "Production Zone C, Line 3",
    "operational_status": "idle",
    "total_operating_hours": 14523.8,
    "hours_since_maintenance": 2.0,
    "rated_power": 12.072739091449794,
    "rated_capacity": 4.311719439367415,
    "capacity_unit": "m/min",
    "last_maintenance_date": null,
    "next_maintenance_date": null,
    "primary_operator": null,
    "notes": "",
    "warranty_expiry": null,
    "purchase_cost": null
  }
},
{
  "model": "machines.machine",
  "pk": 145,
  "fields": {
    "created_at": "2025-08-20T22:47:53.677Z",
    "updated_at": "2025-08-20T22:47:53.677Z",
    "created_by": null,
    "updated_by": null,
    "site_code": "FAB-001",
    "status": "active",
    "machine_id": "WV-AIR-004",
    "name": "Air Jet Loom 04",
    "machine_type": 46,
    "manufacturer": "Picanol",
    "model_number": "OptiMax-i",
    "serial_number": "PIC20235542",
    "installation_date": "2023-11-25",
    "building": "Weaving Shed Building B",
    "floor": "Floor 1",
    "location_details": "Production Zone D, Line 4",
    "operational_status": "idle",
    "total_operating_hours": 9972.1,
    "hours_since_maintenance": 21.0,
    "rated_power": 12.833064778078603,
    "rated_capacity": 4.714891103419713,
    "capacity_unit": "m/min",
    "last_maintenance_date": null,
    "next_maintenance_date": null,
    "primary_operator": null,
    "notes": "",
    "warranty_expiry": null,
    "purchase_cost": null
  }
},
{
  "model": "machines.machine",
  "pk": 146,
  "fields": {
    "created_at": "2025-08-20T22:47:53.686Z",
    "updated_at": "2025-08-20T22:47:53.686Z",
    "created_by": null,
    "updated_by": null,
    "site_code": "FAB-001",
    "status": "active",
    "machine_id": "WV-PRO-005",
    "name": "Projectile Loom 05",
    "machine_type": 47,
    "manufacturer": "Sulzer",
    "model_number": "P7300",
    "serial_number": "SUL20231395",
    "installation_date": "2023-04-02",
    "building": "Weaving Shed Building B",
    "floor": "Floor 2",
    "location_details": "Production Zone A, Line 5",
    "operational_status": "running",
    "total_operating_hours": 14836.2,
    "hours_since_maintenance": 671.0,
    "rated_power": 18.400285606907314,
    "rated_capacity": 2.761545955146546,
    "capacity_unit": "m/min",
    "last_maintenance_date": null,
    "next_maintenance_date": null,
    "primary_operator": null,
    "notes": "",
    "warranty_expiry": null,
    "purchase_cost": null
  }
},
{
  "model": "machines.machine",
  "pk": 147,
  "fields": {
    "created_at": "2025-08-20T22:47:53.697Z",
    "updated_at": "2025-08-20T22:47:53.697Z",
    "created_by": null,
    "updated_by": null,
    "site_code": "FAB-001",
    "status": "active",
    "machine_id": "WV-PRO-006",
    "name": "Projectile Loom 06",
    "machine_type": 47,
    "manufacturer": "Sulzer",
    "model_number": "P7300",
    "serial_number": "SUL20248010",
    "installation_date": "2024-07-16",
    "building": "Weaving Shed Building B",
    "floor": "Floor 3",
    "location_details": "Production Zone B, Line 1",
    "operational_status": "running",
    "total_operating_hours": 6797.6,
    "hours_since_maintenance": 540.0,
    "rated_power": 17.68014235528747,
    "rated_capacity": 2.7860119001712373,
    "capacity_unit": "m/min",
    "last_maintenance_date": null,
    "next_maintenance_date": null,
    "primary_operator": null,
    "notes": "",
    "warranty_expiry": null,
    "purchase_cost": null
  }
}
]
